{
  "version": "6761",
  "date": "Apr 07 2026",
  "time": "13:00:43",
  "changes": {
    "Lua Enums": {
      "added": [
        {
          "type": "enum_member",
          "enum": "GameActivity_t",
          "name": "ACT_DOTA_CAST5_STATUE",
          "value": 1795
        }
      ],
      "removed": [
        {
          "type": "enum_member",
          "enum": "GameActivity_t",
          "name": "ACT_DOTA_TORRENT",
          "value": 1795
        }
      ],
      "changed": []
    },
    "Abilities": {
      "added": [],
      "removed": [],
      "changed": [
        {
          "type": "ability",
          "name": "frostbitten_golem_time_warp_aura",
          "changes": {
            "AbilityValues": {
              "bonus_cdr": {
                "old": "10 11 12 14",
                "new": "8 9 10 11"
              }
            }
          }
        },
        {
          "type": "ability",
          "name": "miniboss_reflect",
          "changes": {
            "AbilityValues": {
              "passive_reflection_bonus_per_interval": {
                "old": 2,
                "new": 1.5
              }
            }
          }
        },
        {
          "type": "ability",
          "name": "ancient_apparition_bone_chill",
          "changes": {
            "AbilityValues": {
              "str_reduction": {
                "value": {
                  "old": 0.2,
                  "new": 0.2
                },
                "hero_levelup": {
                  "old": 0.1,
                  "new": 0.1
                },
                "levelup_interval": {
                  "old": 3,
                  "new": 3
                },
                "special_bonus_scepter": {
                  "old": "+0.3",
                  "new": "+0.8"
                }
              },
              "tooltip_scepter_bonus": {
                "old": 0.3,
                "new": 0.8
              }
            }
          }
        },
        {
          "type": "ability",
          "name": "antimage_mana_break",
          "changes": {
            "AbilityValues": {
              "mana_per_hit_pct": {
                "value": {
                  "old": "1.6 2.4 3.2 4.0",
                  "new": "1.8 2.7 3.6 4.5"
                },
                "special_bonus_scepter": {
                  "old": "+1.5",
                  "new": "+1.5"
                },
                "display_type": {
                  "old": "kManaPercentage",
                  "new": "kManaPercentage"
                }
              }
            }
          }
        },
        {
          "type": "ability",
          "name": "antimage_blink",
          "changes": {
            "AbilityValues": {
              "AbilityCastRange": {
                "value": {
                  "old": "875 950 1025 1100",
                  "new": "875 950 1025 1100"
                },
                "special_bonus_unique_antimage_3": {
                  "old": "+150",
                  "new": "+125"
                }
              }
            }
          }
        },
        {
          "type": "ability",
          "name": "arc_warden_magnetic_field",
          "changes": {
            "AbilityValues": {
              "AbilityCooldown": {
                "value": {
                  "old": "20 19 18 17",
                  "new": "20 19 18 17"
                },
                "special_bonus_unique_arc_warden_9": {
                  "old": -5,
                  "new": -4
                }
              }
            }
          }
        },
        {
          "type": "ability",
          "name": "arc_warden_spark_wraith",
          "changes": {
            "AbilityValues": {
              "spark_damage_base": {
                "value": {
                  "old": "100 170 240 310",
                  "new": "100 170 240 310"
                },
                "special_bonus_unique_arc_warden": {
                  "old": "+200",
                  "new": "+240"
                }
              }
            }
          }
        },
        {
          "type": "ability",
          "name": "arc_warden_runic_infusion",
          "changes": {
            "AbilityValues": {
              "all_attribute_bonus_per_stack": {
                "value": {
                  "old": 1.5,
                  "new": 1.5
                },
                "special_bonus_unique_arc_warden_8": {
                  "old": "+1.5",
                  "new": "+1.0"
                }
              }
            }
          }
        },
        {
          "type": "ability",
          "name": "batrider_sticky_napalm",
          "changes": {
            "AbilityValues": {
              "movement_speed_pct": {
                "value": {
                  "old": "-.75 -1.5 -2.25 -3",
                  "new": "-.75 -1.5 -2.25 -3"
                },
                "special_bonus_unique_batrider_7": {
                  "old": -0.5,
                  "new": -0.75
                }
              }
            }
          }
        },
        {
          "type": "ability",
          "name": "batrider_firefly",
          "changes": {
            "AbilityCooldown": {
              "old": "45 40 35 30",
              "new": "48 42 36 30"
            }
          }
        },
        {
          "type": "ability",
          "name": "beastmaster_wild_axes",
          "changes": {
            "AbilityValues": {
              "duration": {
                "value": {
                  "old": 12,
                  "new": "10 11 12 13"
                }
              },
              "damage_amp": {
                "value": {
                  "old": "5 6 7 8",
                  "new": "5 6 7 8"
                },
                "special_bonus_unique_beastmaster_9": {
                  "old": "+2",
                  "new": "+1.5"
                }
              }
            }
          }
        },
        {
          "type": "ability",
          "name": "bloodseeker_thirst",
          "changes": {
            "AbilityValues": {
              "bonus_movement_speed": {
                "value": {
                  "old": "10 20 30 40",
                  "new": "10 20 30 40"
                },
                "special_bonus_unique_bloodseeker_4": {
                  "old": "+18",
                  "new": "+15"
                }
              }
            }
          }
        },
        {
          "type": "ability",
          "name": "bloodseeker_rupture",
          "changes": {
            "AbilityManaCost": {
              "old": "100 150 200",
              "new": "125 175 225"
            }
          }
        },
        {
          "type": "ability",
          "name": "chaos_knight_phantasm",
          "changes": {
            "AbilityCooldown": {
              "old": 75,
              "new": "85 80 75"
            },
            "AbilityValues": {
              "images_count": {
                "old": "1 2 3",
                "new": 3
              },
              "outgoing_damage": {
                "old": 0,
                "new": "-50 -25 0"
              },
              "outgoing_damage_tooltip": {
                "value": {
                  "old": 100,
                  "new": "50 75 100"
                },
                "CalculateSpellDamageTooltip": {
                  "old": 0,
                  "new": 0
                },
                "DamageTypeTooltip": {
                  "old": "DAMAGE_TYPE_NONE",
                  "new": "DAMAGE_TYPE_NONE"
                }
              }
            }
          }
        },
        {
          "type": "ability",
          "name": "chen_holy_persuasion",
          "changes": {
            "AbilityValues": {
              "damage_bonus": {
                "value": {
                  "old": "0 6 12 18",
                  "new": "5 10 15 20"
                },
                "special_bonus_unique_chen_5": {
                  "old": "+12",
                  "new": "+12"
                }
              }
            }
          }
        },
        {
          "type": "ability",
          "name": "clinkz_strafe",
          "changes": {
            "AbilityValues": {
              "duration": {
                "value": {
                  "old": 3.5,
                  "new": 3.5
                },
                "special_bonus_unique_clinkz_1": {
                  "old": "+0.75",
                  "new": "+1.0"
                }
              }
            }
          }
        },
        {
          "type": "ability",
          "name": "crystal_maiden_crystal_clone",
          "changes": {
            "AbilityCooldown": {
              "old": 10,
              "new": 12
            }
          }
        },
        {
          "type": "ability",
          "name": "dawnbreaker_break_of_dawn",
          "changes": {
            "AbilityValues": {
              "max_dmg_pct": {
                "value": {
                  "old": 10,
                  "new": 8
                },
                "hero_levelup": {
                  "old": "+1",
                  "new": "+1"
                }
              }
            }
          }
        },
        {
          "type": "ability",
          "name": "death_prophet_exorcism",
          "changes": {
            "AbilityValues": {
              "min_damage": {
                "old": 62,
                "new": "62 65 68"
              },
              "max_damage": {
                "old": 67,
                "new": "68 71 74"
              },
              "average_damage": {
                "old": 64,
                "new": "65 68 71"
              }
            }
          }
        },
        {
          "type": "ability",
          "name": "doom_bringer_devour",
          "changes": {
            "AbilityValues": {
              "magic_resist": {
                "value": {
                  "old": 0,
                  "new": 0
                },
                "special_bonus_unique_doom_3": {
                  "old": "+15",
                  "new": null
                }
              }
            }
          }
        },
        {
          "type": "ability",
          "name": "doom_bringer_scorched_earth",
          "changes": {
            "AbilityValues": {
              "damage_per_second": {
                "value": {
                  "old": "20 35 50 65",
                  "new": "20 30 40 50"
                }
              }
            }
          }
        },
        {
          "type": "ability",
          "name": "doom_bringer_infernal_blade",
          "changes": {
            "AbilityValues": {
              "burn_damage_pct": {
                "value": {
                  "old": "1 2 3 4",
                  "new": "1 2 3 4"
                },
                "special_bonus_unique_doom_1": {
                  "old": "+2.5",
                  "new": "+1.5"
                }
              }
            }
          }
        },
        {
          "type": "ability",
          "name": "doom_bringer_doom",
          "changes": {
            "AbilityValues": {
              "damage": {
                "value": {
                  "old": "25 45 66",
                  "new": "22 44 66"
                }
              }
            }
          }
        },
        {
          "type": "ability",
          "name": "drow_ranger_multishot",
          "changes": {
            "AbilityValues": {
              "wave_count": {
                "value": {
                  "old": 3,
                  "new": 3
                },
                "special_bonus_unique_drow_ranger_8": {
                  "old": "+1",
                  "new": "+2"
                }
              }
            }
          }
        },
        {
          "type": "ability",
          "name": "drow_ranger_marksmanship",
          "changes": {
            "AbilityValues": {
              "disable_range": {
                "old": 325,
                "new": 300
              }
            }
          }
        },
        {
          "type": "ability",
          "name": "elder_titan_momentum",
          "changes": {
            "AbilityValues": {
              "armor_from_movespeed": {
                "value": {
                  "old": 3.6,
                  "new": 5
                },
                "hero_levelup": {
                  "old": "+0.4",
                  "new": "+0.5"
                }
              }
            }
          }
        },
        {
          "type": "ability",
          "name": "ember_spirit_sleight_of_fist",
          "changes": {
            "AbilityManaCost": {
              "old": "60 65 70 75",
              "new": 75
            }
          }
        },
        {
          "type": "ability",
          "name": "enigma_demonic_conversion",
          "changes": {
            "AbilityValues": {
              "eidelon_base_damage": {
                "old": "16 27 38 49",
                "new": "16 28 40 52"
              }
            }
          }
        },
        {
          "type": "ability",
          "name": "enigma_event_horizon",
          "changes": {
            "AbilityValues": {
              "speed_bonus": {
                "value": {
                  "old": 4,
                  "new": 5
                },
                "hero_levelup": {
                  "old": "+1",
                  "new": "+1"
                }
              }
            }
          }
        },
        {
          "type": "ability",
          "name": "furion_wrath_of_nature",
          "changes": {
            "AbilityValues": {
              "damage": {
                "value": {
                  "old": "90 130 170",
                  "new": "100 140 180"
                },
                "special_bonus_unique_furion_5": {
                  "old": "+25",
                  "new": "+25"
                }
              }
            }
          }
        },
        {
          "type": "ability",
          "name": "gyrocopter_flak_cannon",
          "changes": {
            "AbilityValues": {
              "AbilityCooldown": {
                "value": {
                  "old": "26 24 22 20",
                  "new": 25
                },
                "special_bonus_unique_gyrocopter_1": {
                  "old": -4,
                  "new": -4
                }
              }
            }
          }
        },
        {
          "type": "ability",
          "name": "gyrocopter_call_down",
          "changes": {
            "AbilityValues": {
              "AbilityCooldown": {
                "value": {
                  "old": "90 75 60",
                  "new": "75 65 55"
                },
                "special_bonus_unique_gyrocopter_5": {
                  "old": -40,
                  "new": -40
                }
              }
            }
          }
        },
        {
          "type": "ability",
          "name": "hoodwink_hunters_boomerang",
          "changes": {
            "AbilityValues": {
              "mark_duration": {
                "old": 7,
                "new": 6
              }
            }
          }
        },
        {
          "type": "ability",
          "name": "invoker_quas",
          "changes": {
            "AbilityValues": {
              "max_level": {
                "value": {
                  "old": 8,
                  "new": 8
                },
                "special_bonus_scepter_1": {
                  "old": "+1",
                  "new": "+1"
                },
                "special_bonus_unique_invoker_orb_levels": {
                  "old": "+1",
                  "new": null
                }
              }
            }
          }
        },
        {
          "type": "ability",
          "name": "invoker_wex",
          "changes": {
            "AbilityValues": {
              "max_level": {
                "value": {
                  "old": 8,
                  "new": 8
                },
                "special_bonus_scepter_2": {
                  "old": "+1",
                  "new": "+1"
                },
                "special_bonus_unique_invoker_orb_levels": {
                  "old": "+1",
                  "new": null
                }
              }
            }
          }
        },
        {
          "type": "ability",
          "name": "invoker_exort",
          "changes": {
            "AbilityValues": {
              "max_level": {
                "value": {
                  "old": 8,
                  "new": 8
                },
                "special_bonus_scepter_3": {
                  "old": "+1",
                  "new": "+1"
                },
                "special_bonus_unique_invoker_orb_levels": {
                  "old": "+1",
                  "new": null
                }
              }
            }
          }
        },
        {
          "type": "ability",
          "name": "invoker_invoke",
          "changes": {
            "AbilityValues": {
              "first_ability_level": {
                "old": null,
                "new": 6
              },
              "second_ability_level": {
                "old": null,
                "new": 12
              },
              "third_ability_level": {
                "old": null,
                "new": 18
              }
            }
          }
        },
        {
          "type": "ability",
          "name": "invoker_forge_spirit",
          "changes": {
            "AbilityValues": {
              "armor_per_attack": {
                "value": {
                  "old": "0.8 0.9 1 1.1 1.2 1.3 1.4 1.5 1.6 1.7 1.8",
                  "new": "0.8 0.9 1 1.1 1.2 1.3 1.4 1.5 1.6 1.7 1.8"
                },
                "levelkey": {
                  "old": "exortlevel",
                  "new": "exortlevel"
                },
                "special_bonus_unique_invoker_forged_spirit_armor_reduction": {
                  "old": null,
                  "new": "+50%"
                }
              }
            }
          }
        },
        {
          "type": "ability",
          "name": "forged_spirit_melting_strike",
          "changes": {
            "AbilityValues": {
              "armor_removed": {
                "value": {
                  "old": null,
                  "new": "0.8 0.9 1 1.1 1.2 1.3 1.4 1.5 1.6 1.7"
                },
                "special_bonus_unique_invoker_forged_spirit_armor_reduction": {
                  "old": null,
                  "new": "+50%"
                },
                "_value": {
                  "old": "0.8 0.9 1 1.1 1.2 1.3 1.4 1.5 1.6 1.7",
                  "new": null
                }
              }
            }
          }
        },
        {
          "type": "ability",
          "name": "jakiro_dual_breath",
          "changes": {
            "AbilityValues": {
              "AbilityCooldown": {
                "value": {
                  "old": 10,
                  "new": "12 11 10 9"
                },
                "special_bonus_unique_jakiro_dualbreath_cooldown": {
                  "old": -3.5,
                  "new": -3.5
                }
              }
            }
          }
        },
        {
          "type": "ability",
          "name": "jakiro_liquid_fire",
          "changes": {
            "AbilityValues": {
              "damage": {
                "value": {
                  "old": "15 25 35 45",
                  "new": "12 24 36 48"
                }
              }
            }
          }
        },
        {
          "type": "ability",
          "name": "jakiro_macropyre",
          "changes": {
            "AbilityManaCost": {
              "old": "300 400 500",
              "new": "250 350 450"
            },
            "AbilityValues": {
              "damage": {
                "value": {
                  "old": "100 150 200",
                  "new": "100 150 200"
                },
                "special_bonus_unique_jakiro_7": {
                  "old": "+20",
                  "new": "+25"
                }
              }
            }
          }
        },
        {
          "type": "ability",
          "name": "juggernaut_blade_fury",
          "changes": {
            "AbilityValues": {
              "blade_fury_damage": {
                "value": {
                  "old": "80 110 140 170",
                  "new": "80 110 140 170"
                },
                "special_bonus_unique_juggernaut": {
                  "old": "+100",
                  "new": "+120"
                }
              }
            }
          }
        },
        {
          "type": "ability",
          "name": "juggernaut_bladeform",
          "changes": {
            "AbilityValues": {
              "agi_bonus_pct_per_stack": {
                "value": {
                  "old": 2.5,
                  "new": 2.5
                },
                "hero_levelup": {
                  "old": "+0.05",
                  "new": "+0.1"
                }
              }
            }
          }
        },
        {
          "type": "ability",
          "name": "keeper_of_the_light_spirit_form",
          "changes": {
            "AbilityValues": {
              "movement_speed": {
                "value": {
                  "old": 50,
                  "new": 50
                },
                "special_bonus_unique_keeper_of_the_light_11": {
                  "old": "+30",
                  "new": "+25"
                }
              },
              "cast_range": {
                "old": "100 200 300",
                "new": "100 175 250"
              }
            }
          }
        },
        {
          "type": "ability",
          "name": "keeper_of_the_light_bright_speed",
          "changes": {
            "AbilityValues": {
              "intelligence_per_speed": {
                "old": 2.5,
                "new": 3
              }
            }
          }
        },
        {
          "type": "ability",
          "name": "largo_song_fight_song",
          "changes": {
            "AbilityValues": {
              "damage_per_stack": {
                "value": {
                  "old": 0,
                  "new": 0
                },
                "special_bonus_scepter": {
                  "old": "+6 +12 +18",
                  "new": "+6 +10 +14"
                },
                "special_bonus_unique_largo_7": {
                  "old": "+6",
                  "new": "+6"
                }
              }
            }
          }
        },
        {
          "type": "ability",
          "name": "largo_croak_of_genius",
          "changes": {
            "AbilityManaCost": {
              "old": "25 35 45 55",
              "new": 40
            },
            "AbilityValues": {
              "duration": {
                "old": "12 18 24 30",
                "new": "15 20 25 30"
              }
            }
          }
        },
        {
          "type": "ability",
          "name": "largo_catchy_lick",
          "changes": {
            "AbilityValues": {
              "damage": {
                "value": {
                  "old": "85 170 255 340",
                  "new": "85 170 255 340"
                },
                "special_bonus_unique_largo_5": {
                  "old": "+170",
                  "new": "+200"
                }
              }
            }
          }
        },
        {
          "type": "ability",
          "name": "largo_encore",
          "changes": {
            "AbilityValues": {
              "buff_amplification": {
                "value": {
                  "old": 9,
                  "new": 10
                },
                "hero_levelup": {
                  "old": "+1",
                  "new": "+1"
                }
              }
            }
          }
        },
        {
          "type": "ability",
          "name": "lycan_shapeshift",
          "changes": {
            "AbilityValues": {
              "AbilityCooldown": {
                "value": {
                  "old": "110 100 90",
                  "new": "105 95 85"
                },
                "special_bonus_unique_lycan_8": {
                  "old": -15,
                  "new": -15
                }
              }
            }
          }
        },
        {
          "type": "ability",
          "name": "meepo_earthbind",
          "changes": {
            "AbilityValues": {
              "AbilityCooldown": {
                "value": {
                  "old": "16 14 12 10",
                  "new": "16 14 12 10"
                },
                "special_bonus_unique_meepo_3": {
                  "old": -2.5,
                  "new": -1.5
                }
              }
            }
          }
        },
        {
          "type": "ability",
          "name": "meepo_ransack",
          "changes": {
            "AbilityValues": {
              "health_steal_heroes": {
                "value": {
                  "old": "9 12 15 18",
                  "new": "7 10 13 16"
                },
                "DamageTypeTooltip": {
                  "old": "DAMAGE_TYPE_PURE",
                  "new": "DAMAGE_TYPE_PURE"
                },
                "special_bonus_unique_meepo_6": {
                  "old": "+7",
                  "new": "+6"
                }
              }
            }
          }
        },
        {
          "type": "ability",
          "name": "meepo_divided_we_stand",
          "changes": {
            "AbilityValues": {
              "attribute_penalty_pct": {
                "old": null,
                "new": 0
              }
            }
          }
        },
        {
          "type": "ability",
          "name": "meepo_megameepo",
          "changes": {
            "AbilityCooldown": {
              "old": 60,
              "new": 90
            },
            "AbilityValues": {
              "duration": {
                "old": 25,
                "new": 20
              }
            }
          }
        },
        {
          "type": "ability",
          "name": "mirana_celestial_quiver",
          "changes": {
            "AbilityValues": {
              "levels_per_quiver_tooltip": {
                "old": 7,
                "new": null
              }
            },
            "EnableChargeDisplayOverride": {
              "old": null,
              "new": 1
            }
          }
        },
        {
          "type": "ability",
          "name": "monkey_king_tree_dance",
          "changes": {
            "AbilityValues": {
              "ground_jump_distance": {
                "value": {
                  "old": 900,
                  "new": 900
                },
                "special_bonus_unique_monkey_king_7": {
                  "old": "+350",
                  "new": "+300"
                }
              },
              "perched_jump_distance": {
                "value": {
                  "old": 900,
                  "new": 900
                },
                "special_bonus_unique_monkey_king_7": {
                  "old": "+350",
                  "new": "+300"
                }
              }
            }
          }
        },
        {
          "type": "ability",
          "name": "monkey_king_transfiguration",
          "changes": {
            "AbilityCooldown": {
              "old": 3,
              "new": 5
            }
          }
        },
        {
          "type": "ability",
          "name": "naga_siren_eelskin",
          "changes": {
            "AbilityValues": {
              "evasion_per_naga": {
                "value": {
                  "old": 4.9,
                  "new": 4
                },
                "hero_levelup": {
                  "old": 0.1,
                  "new": 0.1
                }
              }
            }
          }
        },
        {
          "type": "ability",
          "name": "necrolyte_death_seeker",
          "changes": {
            "AbilityManaCost": {
              "old": 125,
              "new": 160
            }
          }
        },
        {
          "type": "ability",
          "name": "night_stalker_hunter_in_the_night",
          "changes": {
            "AbilityValues": {
              "bonus_movement_speed_pct_night": {
                "value": {
                  "old": 24,
                  "new": 24
                },
                "hero_levelup": {
                  "old": 2,
                  "new": 2
                },
                "levelup_interval": {
                  "old": 3,
                  "new": 3
                },
                "special_bonus_scepter": {
                  "old": "+15",
                  "new": "+15"
                }
              },
              "bonus_attack_speed_night": {
                "value": {
                  "old": 38,
                  "new": 38
                },
                "hero_levelup": {
                  "old": 2,
                  "new": 2
                },
                "special_bonus_scepter": {
                  "old": "+50",
                  "new": "+50"
                }
              }
            }
          }
        },
        {
          "type": "ability",
          "name": "nyx_assassin_vendetta",
          "changes": {
            "AbilityValues": {
              "duration": {
                "value": {
                  "old": 60,
                  "new": "45 50 55"
                }
              }
            }
          }
        },
        {
          "type": "ability",
          "name": "omniknight_hammer_of_purity",
          "changes": {
            "AbilityValues": {
              "heal_pct": {
                "value": {
                  "old": 30,
                  "new": 35
                }
              }
            }
          }
        },
        {
          "type": "ability",
          "name": "omniknight_degen_aura",
          "changes": {
            "AbilityValues": {
              "radius": {
                "value": {
                  "old": 325,
                  "new": 325
                },
                "special_bonus_unique_omniknight_degen_aura_radius": {
                  "old": "+125",
                  "new": "+150"
                },
                "affected_by_aoe_increase": {
                  "old": 1,
                  "new": 1
                }
              }
            }
          }
        },
        {
          "type": "ability",
          "name": "omniknight_guardian_angel",
          "changes": {
            "AbilityValues": {
              "duration": {
                "value": {
                  "old": "4.0 4.5 5",
                  "new": "4.0 4.75 5.5"
                }
              },
              "heal_and_regen_amp": {
                "value": {
                  "old": 0,
                  "new": 0
                },
                "special_bonus_scepter": {
                  "old": "+100",
                  "new": "+50"
                }
              }
            }
          }
        },
        {
          "type": "ability",
          "name": "pangolier_lucky_shot",
          "changes": {
            "AbilityValues": {
              "attack_slow": {
                "old": "40 80 120 160",
                "new": "35 70 105 140"
              }
            }
          }
        },
        {
          "type": "ability",
          "name": "pangolier_gyroshell",
          "changes": {
            "AbilityValues": {
              "damage_pct": {
                "old": 100,
                "new": 80
              }
            }
          }
        },
        {
          "type": "ability",
          "name": "phantom_assassin_phantom_strike",
          "changes": {
            "AbilityValues": {
              "bonus_attack_speed": {
                "value": {
                  "old": "100 130 160 190",
                  "new": "80 120 160 200"
                },
                "special_bonus_unique_phantom_assassin_strike_aspd": {
                  "old": "+60",
                  "new": "+60"
                }
              },
              "duration": {
                "value": {
                  "old": 2.5,
                  "new": 3
                },
                "special_bonus_unique_phantom_assassin_4": {
                  "old": "+0.6",
                  "new": "+0.6"
                }
              }
            }
          }
        },
        {
          "type": "ability",
          "name": "phantom_assassin_coup_de_grace",
          "changes": {
            "AbilityValues": {
              "crit_bonus": {
                "value": {
                  "old": "200 300 400",
                  "new": "200 325 450"
                },
                "special_bonus_facet_phantom_assassin_methodical": {
                  "old": "+100",
                  "new": "+100"
                }
              }
            }
          }
        },
        {
          "type": "ability",
          "name": "phoenix_sun_ray",
          "changes": {
            "AbilityValues": {
              "shard_move_slow_pct": {
                "special_bonus_shard": {
                  "old": 10,
                  "new": null
                },
                "value": {
                  "old": null,
                  "new": 0
                }
              }
            }
          }
        },
        {
          "type": "ability",
          "name": "primal_beast_pulverize",
          "changes": {
            "AbilityCooldown": {
              "old": "40 35 30",
              "new": "45 40 35"
            }
          }
        },
        {
          "type": "ability",
          "name": "pudge_innate_graft_flesh",
          "changes": {
            "AbilityValues": {
              "flesh_heap_strength_buff_amount": {
                "value": {
                  "old": 1.6,
                  "new": 2
                },
                "special_bonus_unique_pudge_1": {
                  "old": "x1.5",
                  "new": "x1.5"
                }
              }
            }
          }
        },
        {
          "type": "ability",
          "name": "rubick_telekinesis",
          "changes": {
            "AbilityValues": {
              "landing_damage": {
                "special_bonus_unique_rubick_8": {
                  "old": 325,
                  "new": 300
                }
              }
            }
          }
        },
        {
          "type": "ability",
          "name": "sandking_epicenter",
          "changes": {
            "AbilityValues": {
              "epicenter_slow_as": {
                "value": {
                  "old": "-50 -55 -60",
                  "new": "-30 -40 -50"
                }
              },
              "spine_damage_pct": {
                "special_bonus_scepter": {
                  "old": "=50",
                  "new": "=40"
                }
              }
            }
          }
        },
        {
          "type": "ability",
          "name": "shadow_demon_disruption",
          "changes": {
            "AbilityValues": {
              "illusion_duration": {
                "old": "11 12 13 14",
                "new": "8 10 12 14"
              }
            }
          }
        },
        {
          "type": "ability",
          "name": "shredder_whirling_death",
          "changes": {
            "AbilityValues": {
              "whirling_damage": {
                "old": "75 120 165 210",
                "new": "60 120 180 240"
              }
            }
          }
        },
        {
          "type": "ability",
          "name": "shredder_timber_chain",
          "changes": {
            "AbilityValues": {
              "damage": {
                "old": "45 100 155 210",
                "new": "45 105 165 225"
              }
            }
          }
        },
        {
          "type": "ability",
          "name": "shredder_chakram",
          "changes": {
            "AbilityValues": {
              "pass_damage": {
                "value": {
                  "old": "100 150 200",
                  "new": "75 150 225"
                }
              }
            }
          }
        },
        {
          "type": "ability",
          "name": "silencer_global_silence",
          "changes": {
            "AbilityValues": {
              "AbilityCooldown": {
                "value": {
                  "old": 120,
                  "new": 120
                },
                "special_bonus_unique_silencer_7": {
                  "old": -20,
                  "new": -15
                }
              }
            }
          }
        },
        {
          "type": "ability",
          "name": "slardar_sprint",
          "changes": {
            "AbilityValues": {
              "AbilityCooldown": {
                "value": {
                  "old": "29 25 21 17",
                  "new": "33 28 23 18"
                }
              }
            }
          }
        },
        {
          "type": "ability",
          "name": "slark_essence_shift",
          "changes": {
            "AbilityValues": {
              "duration": {
                "value": {
                  "old": 12.5,
                  "new": 10
                },
                "hero_levelup": {
                  "old": "+2.5",
                  "new": "+2.5"
                },
                "special_bonus_unique_slark_4": {
                  "old": "+25",
                  "new": "+20"
                }
              }
            }
          }
        },
        {
          "type": "ability",
          "name": "snapfire_scatterblast",
          "changes": {
            "AbilityCooldown": {
              "old": "18 15 12 9",
              "new": "17 14 11 8"
            },
            "AbilityValues": {
              "blast_width_initial": {
                "value": {
                  "old": 225,
                  "new": 250
                },
                "special_bonus_facet_snapfire_full_bore": {
                  "old": "=75",
                  "new": "=75"
                },
                "affected_by_aoe_increase": {
                  "old": 1,
                  "new": 1
                }
              }
            }
          }
        },
        {
          "type": "ability",
          "name": "spectre_spectral_dagger",
          "changes": {
            "AbilityValues": {
              "AbilityCooldown": {
                "value": {
                  "old": "22 20 18 16",
                  "new": "22 20 18 16"
                },
                "special_bonus_unique_spectre": {
                  "old": -4,
                  "new": -3
                }
              }
            }
          }
        },
        {
          "type": "ability",
          "name": "spectre_dispersion",
          "changes": {
            "AbilityValues": {
              "max_radius": {
                "value": {
                  "old": 800,
                  "new": 700
                },
                "affected_by_aoe_increase": {
                  "old": 1,
                  "new": 1
                }
              }
            }
          }
        },
        {
          "type": "ability",
          "name": "techies_suicide",
          "changes": {
            "AbilityValues": {
              "damage": {
                "value": {
                  "old": "200 300 400 500",
                  "new": "200 300 400 500"
                },
                "special_bonus_unique_techies": {
                  "old": "+200",
                  "new": "+175"
                }
              }
            }
          }
        },
        {
          "type": "ability",
          "name": "terrorblade_conjure_image",
          "changes": {
            "AbilityValues": {
              "illusion_duration": {
                "value": {
                  "old": 34,
                  "new": 34
                },
                "special_bonus_unique_terrorblade_5": {
                  "old": "+10",
                  "new": "+8"
                }
              }
            }
          }
        },
        {
          "type": "ability",
          "name": "tidehunter_gush",
          "changes": {
            "AbilityValues": {
              "gush_damage": {
                "value": {
                  "old": "100 160 220 280",
                  "new": "100 160 220 280"
                },
                "special_bonus_unique_tidehunter_2": {
                  "old": "+100",
                  "new": "+90"
                }
              }
            }
          }
        },
        {
          "type": "ability",
          "name": "tidehunter_anchor_smash",
          "changes": {
            "AbilityValues": {
              "building_pct_damage": {
                "value": {
                  "old": null,
                  "new": 0
                },
                "special_bonus_unique_tidehunter_10": {
                  "old": null,
                  "new": "+50"
                }
              }
            }
          }
        },
        {
          "type": "ability",
          "name": "tinker_deploy_turrets",
          "changes": {
            "AbilityValues": {
              "missile_speed": {
                "value": {
                  "old": 1200,
                  "new": 1350
                }
              },
              "activation_time": {
                "value": {
                  "old": 0.3,
                  "new": 0
                },
                "special_bonus_scepter": {
                  "old": -0.3,
                  "new": null
                }
              }
            }
          }
        },
        {
          "type": "ability",
          "name": "treant_natures_grasp",
          "changes": {
            "AbilityCooldown": {
              "old": "20 19 18 17",
              "new": "23 21 19 17"
            }
          }
        },
        {
          "type": "ability",
          "name": "tusk_drinking_buddies",
          "changes": {
            "AbilityBehavior": {
              "old": "DOTA_ABILITY_BEHAVIOR_UNIT_TARGET| DOTA_ABILITY_BEHAVIOR_ALT_CASTABLE",
              "new": "DOTA_ABILITY_BEHAVIOR_UNIT_TARGET"
            },
            "AbilityValues": {
              "armor_bonus": {
                "value": {
                  "old": 10,
                  "new": 7
                }
              }
            }
          }
        },
        {
          "type": "ability",
          "name": "tusk_bitter_chill",
          "changes": {
            "AbilityValues": {
              "attack_speed_slow": {
                "value": {
                  "old": 17,
                  "new": 12
                },
                "hero_levelup": {
                  "old": "+3",
                  "new": "+3"
                }
              }
            }
          }
        },
        {
          "type": "ability",
          "name": "visage_gravekeepers_cloak",
          "changes": {
            "AbilityValues": {
              "minimum_damage_familiars": {
                "old": null,
                "new": 0
              }
            }
          }
        },
        {
          "type": "ability",
          "name": "void_spirit_dissimilate",
          "changes": {
            "AbilityDamage": {
              "old": "120 200 280 360",
              "new": "105 185 265 345"
            }
          }
        },
        {
          "type": "ability",
          "name": "windrunner_gale_force",
          "changes": {
            "AbilityCooldown": {
              "old": 30,
              "new": 25
            }
          }
        },
        {
          "type": "ability",
          "name": "windrunner_powershot",
          "changes": {
            "AbilityValues": {
              "slow": {
                "value": {
                  "old": "20 25 30 35",
                  "new": "22 28 34 40"
                }
              }
            }
          }
        },
        {
          "type": "ability",
          "name": "item_holy_locket",
          "changes": {
            "AbilityValues": {
              "heal_increase_passive": {
                "old": 15,
                "new": 10
              },
              "incoming_heal_increase_active": {
                "old": 10,
                "new": 15
              }
            }
          }
        },
        {
          "type": "ability",
          "name": "item_consecrated_wraps",
          "changes": {
            "AbilityValues": {
              "bonus_all_stats": {
                "old": 6,
                "new": 5
              },
              "stack_gain_time": {
                "old": 3,
                "new": 4
              },
              "barrier_cd": {
                "old": 0,
                "new": null
              }
            },
            "ItemDisassembleRule": {
              "old": null,
              "new": "DOTA_ITEM_DISASSEMBLE_NEVER"
            },
            "EnableChargeDisplayOverride": {
              "old": null,
              "new": 1
            },
            "ItemInitialCharges": {
              "old": null,
              "new": 3
            },
            "ItemRequiresCharges": {
              "old": null,
              "new": 1
            },
            "ItemDisplayCharges": {
              "old": null,
              "new": 1
            },
            "AbilityCharges": {
              "old": null,
              "new": 3
            },
            "AbilityChargeRestoreTime": {
              "old": null,
              "new": 3
            },
            "AbilityCooldown": {
              "old": null,
              "new": 0
            },
            "ItemPermanent": {
              "old": null,
              "new": 1
            }
          }
        },
        {
          "type": "ability",
          "name": "item_sange_and_yasha",
          "changes": {
            "AbilityValues": {
              "hp_regen_amp": {
                "old": 20,
                "new": 16
              }
            }
          }
        },
        {
          "type": "ability",
          "name": "item_kaya_and_sange",
          "changes": {
            "AbilityValues": {
              "hp_regen_amp": {
                "old": 20,
                "new": 16
              }
            }
          }
        },
        {
          "type": "ability",
          "name": "item_sange",
          "changes": {
            "AbilityValues": {
              "hp_regen_amp": {
                "old": 16,
                "new": 12
              }
            }
          }
        },
        {
          "type": "ability",
          "name": "item_helm_of_the_overlord",
          "changes": {
            "AbilityCooldown": {
              "old": 45,
              "new": 40
            },
            "AbilityValues": {
              "health_min": {
                "old": 1800,
                "new": 1900
              }
            }
          }
        },
        {
          "type": "ability",
          "name": "item_gungir",
          "changes": {
            "AbilityValues": {
              "radius": {
                "value": {
                  "old": 275,
                  "new": 325
                },
                "affected_by_aoe_increase": {
                  "old": 1,
                  "new": 1
                }
              },
              "radius_tooltip": {
                "value": {
                  "old": 350,
                  "new": 400
                },
                "affected_by_aoe_increase": {
                  "old": 1,
                  "new": 1
                }
              }
            }
          }
        },
        {
          "type": "ability",
          "name": "item_mage_slayer",
          "changes": {
            "AbilityValues": {
              "bonus_magical_armor": {
                "old": 20,
                "new": 18
              },
              "bonus_health_regen": {
                "old": 6,
                "new": 5.5
              }
            }
          }
        },
        {
          "type": "ability",
          "name": "item_abyssal_blade",
          "changes": {
            "AbilityValues": {
              "hp_regen_amp": {
                "old": 20,
                "new": 16
              }
            }
          }
        },
        {
          "type": "ability",
          "name": "item_heavens_halberd",
          "changes": {
            "AbilityValues": {
              "bonus_health_regen": {
                "old": 6,
                "new": 6.5
              }
            }
          }
        },
        {
          "type": "ability",
          "name": "item_minotaur_horn",
          "changes": {
            "AbilityValues": {
              "magic_resist": {
                "old": 50,
                "new": 60
              }
            }
          }
        },
        {
          "type": "ability",
          "name": "item_rattlecage",
          "changes": {
            "AbilityValues": {
              "projectile_damage": {
                "value": {
                  "old": 110,
                  "new": 90
                },
                "apply_curio_bonus": {
                  "old": 1,
                  "new": 1
                }
              }
            }
          }
        },
        {
          "type": "ability",
          "name": "item_enhancement_crude",
          "changes": {
            "AbilityValues": {
              "health_restoration": {
                "old": "10 15 20",
                "new": "9 12 15"
              }
            }
          }
        },
        {
          "type": "ability",
          "name": "item_jidi_pollen_bag",
          "changes": {
            "AbilityValues": {
              "debuff_radius": {
                "old": 700,
                "new": 900
              }
            }
          }
        },
        {
          "type": "ability",
          "name": "item_riftshadow_prism",
          "changes": {
            "AbilityCooldown": {
              "old": 30,
              "new": 27
            }
          }
        },
        {
          "type": "ability",
          "name": "item_metamorphic_mandible",
          "changes": {
            "AbilityValues": {
              "bonus_movespeed": {
                "old": 15,
                "new": 20
              }
            }
          }
        },
        {
          "type": "ability",
          "name": "item_idol_of_screeauk",
          "changes": {
            "AbilityValues": {
              "duration": {
                "value": {
                  "old": 5,
                  "new": 6.5
                },
                "apply_curio_bonus": {
                  "old": 1,
                  "new": 1
                }
              }
            }
          }
        },
        {
          "type": "ability",
          "name": "item_enchanters_bauble",
          "changes": {
            "AbilityValues": {
              "enchantment_bonus_base": {
                "old": 15,
                "new": 10
              }
            }
          }
        },
        {
          "type": "ability",
          "name": "item_conjurers_catalyst",
          "changes": {
            "AbilityValues": {
              "damage_threshold": {
                "old": 100,
                "new": 200
              },
              "damage": {
                "value": {
                  "old": 40,
                  "new": 80
                },
                "apply_curio_bonus": {
                  "old": 1,
                  "new": 1
                }
              },
              "damage_creep": {
                "value": {
                  "old": 15,
                  "new": 30
                },
                "apply_curio_bonus": {
                  "old": 1,
                  "new": 1
                }
              },
              "cooldown": {
                "old": null,
                "new": 0.1
              }
            }
          }
        }
      ]
    },
    "Units": {
      "added": [],
      "removed": [],
      "changed": [
        {
          "type": "unit",
          "name": "npc_dota_necronomicon_warrior_3",
          "changes": {
            "Ability3": {
              "old": "necronomicon_warrior_sight",
              "new": "creep_irresolute"
            },
            "Ability4": {
              "old": "creep_irresolute",
              "new": ""
            }
          }
        },
        {
          "type": "unit",
          "name": "npc_dota_invoker_forged_spirit",
          "changes": {
            "Ability2": {
              "old": "",
              "new": "special_bonus_unique_invoker_forged_spirit_armor_reduction"
            }
          }
        },
        {
          "type": "unit",
          "name": "npc_dota_hero_drow_ranger",
          "changes": {
            "AttributeBaseAgility": {
              "old": 22,
              "new": 24
            }
          }
        },
        {
          "type": "unit",
          "name": "npc_dota_hero_juggernaut",
          "changes": {
            "MovementSpeed": {
              "old": 300,
              "new": 305
            }
          }
        },
        {
          "type": "unit",
          "name": "npc_dota_hero_tiny",
          "changes": {
            "AttributeIntelligenceGain": {
              "old": 2.2,
              "new": 2.4
            }
          }
        },
        {
          "type": "unit",
          "name": "npc_dota_hero_windrunner",
          "changes": {
            "StatusHealthRegen": {
              "old": null,
              "new": 0.75
            }
          }
        },
        {
          "type": "unit",
          "name": "npc_dota_hero_shadow_shaman",
          "changes": {
            "AttributeIntelligenceGain": {
              "old": 3.5,
              "new": 3.3
            }
          }
        },
        {
          "type": "unit",
          "name": "npc_dota_hero_tidehunter",
          "changes": {
            "AttributeBaseStrength": {
              "old": 26,
              "new": 25
            }
          }
        },
        {
          "type": "unit",
          "name": "npc_dota_hero_beastmaster",
          "changes": {
            "Ability10": {
              "old": "special_bonus_armor_5",
              "new": "special_bonus_armor_4"
            },
            "BaseAttackSpeed": {
              "old": 100,
              "new": 90
            }
          }
        },
        {
          "type": "unit",
          "name": "npc_dota_hero_phantom_assassin",
          "changes": {
            "AttributeStrengthGain": {
              "old": 2,
              "new": 2.2
            }
          }
        },
        {
          "type": "unit",
          "name": "npc_dota_hero_night_stalker",
          "changes": {
            "StatusHealthRegen": {
              "old": 1.5,
              "new": 0.25
            }
          }
        },
        {
          "type": "unit",
          "name": "npc_dota_hero_broodmother",
          "changes": {
            "AttributeBaseAgility": {
              "old": 18,
              "new": 20
            }
          }
        },
        {
          "type": "unit",
          "name": "npc_dota_hero_batrider",
          "changes": {
            "ArmorPhysical": {
              "old": 2,
              "new": 1
            }
          }
        },
        {
          "type": "unit",
          "name": "npc_dota_hero_spectre",
          "changes": {
            "AttributeStrengthGain": {
              "old": 2.4,
              "new": 2.3
            }
          }
        },
        {
          "type": "unit",
          "name": "npc_dota_hero_doom_bringer",
          "changes": {
            "Ability10": {
              "old": "special_bonus_unique_doom_3",
              "new": "special_bonus_magic_resistance_10"
            },
            "Ability13": {
              "old": "special_bonus_attack_damage_66",
              "new": "special_bonus_unique_doom_1"
            },
            "Ability15": {
              "old": "special_bonus_unique_doom_1",
              "new": "special_bonus_attack_damage_66"
            }
          }
        },
        {
          "type": "unit",
          "name": "npc_dota_hero_alchemist",
          "changes": {
            "Ability10": {
              "old": "special_bonus_unique_alchemist_5",
              "new": "special_bonus_unique_alchemist_weaponry_power"
            },
            "Ability12": {
              "old": "special_bonus_unique_alchemist_weaponry_power",
              "new": "special_bonus_unique_alchemist_5"
            },
            "AttributeBaseAgility": {
              "old": 22,
              "new": 19
            }
          }
        },
        {
          "type": "unit",
          "name": "npc_dota_hero_invoker",
          "changes": {
            "Ability22": {
              "old": "special_bonus_unique_invoker_orb_levels",
              "new": "special_bonus_unique_invoker_forged_spirit_armor_reduction"
            }
          }
        },
        {
          "type": "unit",
          "name": "npc_dota_hero_shadow_demon",
          "changes": {
            "Ability12": {
              "old": "special_bonus_movement_speed_25",
              "new": "special_bonus_movement_speed_20"
            }
          }
        },
        {
          "type": "unit",
          "name": "npc_dota_hero_meepo",
          "changes": {
            "Ability11": {
              "old": "special_bonus_unique_meepo_2",
              "new": "special_bonus_unique_meepo_3"
            },
            "Ability13": {
              "old": "special_bonus_unique_meepo_3",
              "new": "special_bonus_unique_meepo_2"
            },
            "AttributeStrengthGain": {
              "old": 2.2,
              "new": 2
            },
            "MovementSpeed": {
              "old": 315,
              "new": 310
            }
          }
        },
        {
          "type": "unit",
          "name": "npc_dota_hero_naga_siren",
          "changes": {
            "BaseAttackSpeed": {
              "old": 110,
              "new": 100
            }
          }
        },
        {
          "type": "unit",
          "name": "npc_dota_hero_magnataur",
          "changes": {
            "NameAliases": {
              "old": "magnataur",
              "new": "magnataur, magnus"
            },
            "magnus, workshop_guide_name": {
              "old": "Magnus",
              "new": null
            },
            "AttributeAgilityGain": {
              "old": 2,
              "new": 2.2
            },
            "workshop_guide_name": {
              "old": null,
              "new": "Magnus"
            }
          }
        },
        {
          "type": "unit",
          "name": "npc_dota_hero_skywrath_mage",
          "changes": {
            "StatusManaRegen": {
              "old": 0.25,
              "new": 0.5
            }
          }
        },
        {
          "type": "unit",
          "name": "npc_dota_hero_ember_spirit",
          "changes": {
            "AttackDamageMin": {
              "old": 33,
              "new": 30
            },
            "AttackDamageMax": {
              "old": 37,
              "new": 34
            }
          }
        },
        {
          "type": "unit",
          "name": "npc_dota_hero_phoenix",
          "changes": {
            "AttackRange": {
              "old": 525,
              "new": 500
            }
          }
        },
        {
          "type": "unit",
          "name": "npc_dota_hero_techies",
          "changes": {
            "Ability10": {
              "old": "special_bonus_magic_resistance_20",
              "new": "special_bonus_magic_resistance_15"
            }
          }
        },
        {
          "type": "unit",
          "name": "npc_dota_hero_arc_warden",
          "changes": {
            "Ability14": {
              "old": "special_bonus_unique_arc_warden",
              "new": "special_bonus_unique_arc_warden_7"
            },
            "Ability17": {
              "old": "special_bonus_unique_arc_warden_7",
              "new": "special_bonus_unique_arc_warden"
            }
          }
        },
        {
          "type": "unit",
          "name": "npc_dota_hero_dawnbreaker",
          "changes": {
            "NameAliases": {
              "old": "Dawnbreaker",
              "new": "Dawnbreaker, Valora"
            },
            "Valora, Adjectives": {
              "Female": {
                "old": 1,
                "new": null
              },
              "Fiery": {
                "old": 1,
                "new": null
              }
            },
            "Adjectives": {
              "Female": {
                "old": null,
                "new": 1
              },
              "Fiery": {
                "old": null,
                "new": 1
              }
            }
          }
        },
        {
          "type": "unit",
          "name": "npc_dota_hero_primal_beast",
          "changes": {
            "Ability10": {
              "old": "special_bonus_attack_damage_30",
              "new": "special_bonus_attack_damage_25"
            }
          }
        }
      ]
    },
    "Ability KV Properties": {
      "added": [
        {
          "type": "kv_property",
          "name": "EnableChargeDisplayOverride"
        }
      ],
      "removed": [],
      "changed": []
    }
  }
}